.gitignore
HISTORY.txt
MANIFEST.in
README.rst
bootstrap.py
bootstrap_v1.py
setup.py
test-buildout-1.x.cfg
test-buildout-2.x.cfg
docs/LICENSE.GPL
docs/LICENSE.txt
ftw/__init__.py
ftw.recipe.deployment.egg-info/PKG-INFO
ftw.recipe.deployment.egg-info/SOURCES.txt
ftw.recipe.deployment.egg-info/dependency_links.txt
ftw.recipe.deployment.egg-info/entry_points.txt
ftw.recipe.deployment.egg-info/namespace_packages.txt
ftw.recipe.deployment.egg-info/not-zip-safe
ftw.recipe.deployment.egg-info/requires.txt
ftw.recipe.deployment.egg-info/top_level.txt
ftw/recipe/__init__.py
ftw/recipe/deployment/README.txt
ftw/recipe/deployment/__init__.py
ftw/recipe/deployment/filebeat.py
ftw/recipe/deployment/logrotate.py
ftw/recipe/deployment/pack.py
ftw/recipe/deployment/rc.py
ftw/recipe/deployment/tests.py
ftw/recipe/deployment/utils.py