Metadata-Version: 1.1
Name: ftw.recipe.deployment
Version: 1.4.1
Summary: A zc.buildout recipe for Plone deployments which configures various unix system services.
Home-page: https://github.com/4teamwork/ftw.recipe.deployment
Author: 4teamwork AG
Author-email: mailto:info@4teamwork.ch
License: GPL2
Platform: UNKNOWN
Classifier: Framework :: Buildout :: Recipe
Classifier: Intended Audience :: Developers
Classifier: License :: OSI Approved :: Zope Public License
Classifier: Programming Language :: Python
Classifier: Topic :: Software Development :: Build Tools
